oimbot/__init__.py
oimbot-10.5.8.dist-info/METADATA
oimbot-10.5.8.dist-info/WHEEL
oimbot-10.5.8.dist-info/top_level.txt
oimbot-10.5.8.dist-info/RECORD
