Metadata-Version: 2.1
Name: oimbot
Version: 10.5.8
Summary: Lobby_Bot_Ftn
Home-page: https://bot.aerozoff.com
Author: Aeroz
Classifier: Programming Language :: Python :: 3
Classifier: License :: OSI Approved :: MIT License
Classifier: Operating System :: OS Independent
Requires-Dist: crayons
Requires-Dist: BenBotAsync
Requires-Dist: FortniteAPIAsync
Requires-Dist: sanic ==21.6.2
Requires-Dist: colorama
Requires-Dist: aiohttp
